{
  "Ezreal": ["hybrid", "mana_user", "has_cc", "ad_primary", "ap_primary"],
  "Jinx": ["ad_primary", "mana_user", "has_cc"],
  "Ashe": ["ad_primary", "mana_user", "has_cc"],
  "Ornn": ["tank_kit", "mana_user", "has_cc", "ap_primary"],
  "Leona": ["tank_kit", "mana_user", "has_cc"],
  "Shen": ["tank_kit", "mana_user", "has_cc"],
  "Sylas": ["ap_primary", "mana_user", "has_cc"],
  "Kassadin": ["ap_primary", "mana_user", "has_cc"],
  "Karma": ["ap_primary", "mana_user", "has_cc"],
  "Thresh": ["tank_kit", "mana_user", "has_cc"],
  "Varus": ["hybrid", "mana_user", "has_cc", "ad_primary"],
  "Ziggs": ["ap_primary", "mana_user", "has_cc"],
  "Maokai": ["tank_kit", "mana_user", "has_cc", "ap_primary"],
  "Sona": ["ap_primary", "mana_user", "has_cc"],
  "Soraka": ["ap_primary", "mana_user", "has_cc"],
  "Yone": ["ad_primary", "ap_primary", "mana_user", "has_cc"],
  "Zed": ["ad_primary", "no_mana", "has_cc"],
  "Katarina": ["ap_primary", "no_mana", "no_cc"],
  "Mundo": ["tank_kit", "no_mana", "no_cc"],
  "Brand": ["ap_primary", "mana_user", "has_cc"],
  "Master Yi": ["ad_primary", "no_mana", "no_cc"],
  "Garen": ["ad_primary", "no_mana", "no_cc"],
  "Vladimir": ["ap_primary", "no_mana", "has_cc"],
  "Mordekaiser": ["ap_primary", "no_mana", "has_cc"],
  "Yuumi": ["ap_primary", "mana_user", "has_cc"]
}
